README.md
setup.py
onelink/__init__.py
onelink/generator.py
onelink/utils.py
onelink.egg-info/PKG-INFO
onelink.egg-info/SOURCES.txt
onelink.egg-info/dependency_links.txt
onelink.egg-info/requires.txt
onelink.egg-info/top_level.txt
tests/__init__.py
tests/test_generator.py