Metadata-Version: 2.2
Name: onelink
Version: 0.1.6
Summary: Custom OneLink generator for Android and iOS.
Author: Jegan Rajaiya
Author-email: jeganrajaiya@gmail.com
Classifier: Programming Language :: Python :: 3
Classifier: License :: OSI Approved :: MIT License
Classifier: Operating System :: OS Independent
Requires-Python: >=3.6
Requires-Dist: requests
Dynamic: author
Dynamic: author-email
Dynamic: classifier
Dynamic: description
Dynamic: description-content-type
Dynamic: requires-dist
Dynamic: requires-python
Dynamic: summary
